privatejet/__init__.py
privatejet/boilerplates/main.py
privatejet/cli.py
privatejet/main.py
privatejet/middlewares.py
privatejet/router.py
privatejet-0.0.3.dist-info/LICENSE.txt
privatejet-0.0.3.dist-info/METADATA
privatejet-0.0.3.dist-info/WHEEL
privatejet-0.0.3.dist-info/RECORD
