Metadata-Version: 2.1
Name: privatejet
Version: 0.0.3
Summary: This is a python backend framework for building REST applications. It is built on top of the ASGI specification and uses the uvicorn server.
License: MIT
Author: m-moein98
Author-email: moein1475963.mmz@gmail.com
Requires-Python: >=3.12,<4.0
Classifier: License :: OSI Approved :: MIT License
Classifier: Programming Language :: Python :: 3
Classifier: Programming Language :: Python :: 3.12
Requires-Dist: black (>=23.12.1,<24.0.0)
Requires-Dist: flake8 (>=7.0.0,<8.0.0)
Requires-Dist: isort (>=5.13.2,<6.0.0)
Requires-Dist: mypy (>=1.8.0,<2.0.0)
Requires-Dist: pre-commit (>=3.6.0,<4.0.0)
Requires-Dist: ruff (>=0.1.13,<0.2.0)
Requires-Dist: setuptools (>=69.0.3,<70.0.0)
Requires-Dist: stubs (>=1.0.0,<2.0.0)
Requires-Dist: wheel (>=0.42.0,<0.43.0)
